paralleladb/__init__.py
paralleladb/_devices_mgr.py
paralleladb/_exceptions.py
paralleladb/_parallel_adb.py
parallel_adb-0.0.1.dist-info/LICENSE
parallel_adb-0.0.1.dist-info/METADATA
parallel_adb-0.0.1.dist-info/WHEEL
parallel_adb-0.0.1.dist-info/top_level.txt
parallel_adb-0.0.1.dist-info/RECORD
