Metadata-Version: 2.1
Name: parallel-adb
Version: 0.0.1
Summary: Enable adb command parallel run in all connected devices.
Home-page: https://github.com/jnhyperion/ParallelADB
Author: Johnny Huang
Author-email: jnhyperion@gmail.com
License: UNKNOWN
Keywords: adb command parallel
Platform: UNKNOWN
Classifier: Programming Language :: Python :: 3
Classifier: License :: OSI Approved :: MIT License
Classifier: Operating System :: OS Independent
Requires-Python: >=3.6
